<powerpagecomponent powerpagecomponentid="6e850299-5c00-4b5d-bab0-947be5720c3d">
  <content>{"display_name":"Search/Title","value":"&lt;span&gt;Search&lt;/span&gt;\r\n"}</content>
  <iscustomizable>1</iscustomizable>
  <name>Search/Title</name>
  <powerpagecomponenttype>7</powerpagecomponenttype>
  <powerpagesiteid>
    <powerpagesiteid>1e2dbbcf-3ca0-4b73-a3e2-fa512538c9c6</powerpagesiteid>
  </powerpagesiteid>
  <powerpagesitelanguageid>
    <powerpagesitelanguageid>f1651072-f543-4c06-86b5-a80aa9627f75</powerpagesitelanguageid>
  </powerpagesitelanguageid>
  <statecode>0</statecode>
  <statuscode>1</statuscode>
</powerpagecomponent>